cfnexec/__init__.py
cfnexec/main.py
cfnexec/version.py
cfnexec-0.8.8.dist-info/LICENSE
cfnexec-0.8.8.dist-info/METADATA
cfnexec-0.8.8.dist-info/WHEEL
cfnexec-0.8.8.dist-info/entry_points.txt
cfnexec-0.8.8.dist-info/top_level.txt
cfnexec-0.8.8.dist-info/zip-safe
cfnexec-0.8.8.dist-info/RECORD
