Metadata-Version: 2.1
Name: cfnexec
Version: 0.8.8
Summary: This is Wrapper tool for aws cloudformation create stack.
Home-page: https://github.com/Takenori-Kusaka/cfn-exec
Author: Takenori Kusaka
Author-email: takenori.kusaka@gmail.com
License: MIT
Keywords: aws
Platform: UNKNOWN
Classifier: Intended Audience :: Developers
Classifier: License :: OSI Approved :: MIT License
Classifier: Natural Language :: Japanese
Classifier: Programming Language :: Python :: 3.7
Classifier: Programming Language :: Python :: 3.8
Classifier: Programming Language :: Python :: 3.9
Classifier: Programming Language :: Python :: 3.10
Requires-Python: >=3.7
License-File: LICENSE
Requires-Dist: requests
Requires-Dist: awscli
Requires-Dist: boto3
Requires-Dist: tabulate
